setup.py
AnyCAD/AnyCAD.Common.Core.dll
AnyCAD/AnyCAD.Common.Glad.dll
AnyCAD/AnyCAD.Common.SDL2.dll
AnyCAD/AnyCAD.Common.Zip.dll
AnyCAD/AnyCAD.Data.Kernel.dll
AnyCAD/AnyCAD.Data.View.dll
AnyCAD/AnyCAD.Geometry.Builder.dll
AnyCAD/AnyCAD.Geometry.Interop.dll
AnyCAD/AnyCAD.Geometry.Kernel.dll
AnyCAD/AnyCAD.Graphics.Asset.dll
AnyCAD/AnyCAD.Graphics.Data.dll
AnyCAD/AnyCAD.Graphics.Interop.dll
AnyCAD/AnyCAD.Graphics.Kernel.dll
AnyCAD/AnyCAD.Graphics.Renderer.dll
AnyCAD/AnyCAD.Graphics.View.dll
AnyCAD/AnyCAD.Graphics.Window.dll
AnyCAD/PyAnyCAD.py
AnyCAD/PyAnyUtil.py
AnyCAD/SamCoreInterop.dll
AnyCAD/SamCoreKernel.dll
AnyCAD/SamCoreModeling.dll
AnyCAD/_PyAnyCAD.pyd
AnyCAD/__init__.py
AnyCAD.egg-info/PKG-INFO
AnyCAD.egg-info/SOURCES.txt
AnyCAD.egg-info/dependency_links.txt
AnyCAD.egg-info/top_level.txt