Metadata-Version: 1.0
Name: AnyCAD
Version: 2022.4.9
Summary: a library for 3D Graphics/Geometry Developer
Home-page: http://www.anycad.cn
Author: AnyCAD
Author-email: anycad@anycad.cn
License: MIT License
Keywords: AnyCAD
Platform: any
